Workbook

Sheet Compte de résultats
B2: Emeline SIRON | G2: ANNÉE : | H2: 2025
B3: Compte de résultats
B5: CASH-FLOW | C5: Actuel | F5: Objectif | G5: Delta
C6: Lui | D6: Elle | E6: Foyer | F6: Goal | G6: ∆
B8: Total Revenus | C8: =C38 | D8: =D38 | E8: =E38 | F8: =F38 | G8: =E8-F8
B9: Total Dépenses | C9: =C122 | D9: =D122 | E9: =E122 | F9: =F122 | G9: =E9-F9
B11: TOTAL CASH-FLOW MENSUEL | C11: =C8-C9 | D11: =D8-D9 | E11: =E8-E9 | F11: =F8-F9 | G11: =E11-F11
B12: TOTAL CASH-FLOW ANNUEL | C12: =C11*12 | D12: =D11*12 | E12: =E11*12 | F12: =F11*12 | G12: =E12-F12
B15: REVENUS MENSUELS | C15: Actuel | F15: Objectif | G15: Delta | H15: Pourcentage
C16: Lui | D16: Elle | E16: Foyer | F16: Goal | G16: ∆
B17: ACTIFS
B18: Travail : Salaire | C18: 1500 | D18: 1200 | E18: =C18+D18 | F18: 6000 | G18: =E18-F18
B19: Travail : Prime | C19: 100 | E19: =C19+D19 | G19: =E19-F19
B20: Travail : Commission | D20: 100 | E20: =C20+D20 | G20: =E20-F20
B21: Travail : Bonus | C21: 50 | E21: =C21+D21 | G21: =E21-F21
B22: Travail : Dividende | D22: 50 | E22: =C22+D22 | G22: =E22-F22
B23: Travail : Micro-entrepreneur | C23: 150 | E23: =C23+D23 | G23: =E23-F23
B24: Autres sources | C24: 25 | E24: =C24+D24 | G24: =E24-F24
B25: TOTAL DES REVENUS ACTIFS | C25: =SUM(C18:C24) | D25: =SUM(D18:D24) | E25: =C25+D25 | F25: =SUM(F18:F24) | G25: =E25-F25 | H25: =PRODUCT(E25,1)/$E$38
B27: PASSIFS
B28: Immobilier : Loyers | C28: 1000 | E28: =C28+D28 | F28: 6000 | G28: =E28-F28
B29: Immobilier : Dividendes | D29: 500 | E29: =C29+D29 | G29: =E29-F29
B30: Bourse : Dividendes | C30: 550 | E30: =C30+D30 | G30: =E30-F30
B31: Bourse : Trading | D31: 650 | E31: =C31+D31 | G31: =E31-F31
B32: Private Equity | C32: 350 | D32: 300 | E32: =C32+D32 | G32: =E32-F32
B33: Crowdfunding | C33: 150 | D33: 250 | E33: =C33+D33 | G33: =E33-F33
B34: Autres sources | D34: 150 | E34: =C34+D34 | G34: =E34-F34
B35: TOTAL DES REVENUS PASSIFS | C35: =SUM(C28:C34) | D35: =SUM(D28:D34) | E35: =C35+D35 | F35: =SUM(F28:F34) | G35: =E35-F35 | H35: =PRODUCT(E35,1)/$E$38
B38: TOTAL REVENUS MENSUELS | C38: =C25+C35 | D38: =D25+D35 | E38: =E25+E35 | F38: =F25+F35 | G38: =E38-F38
B39: TOTAL REVENUS ANNUELS | C39: =C38*12 | D39: =D38*12 | E39: =E38*12 | F39: =F38*12 | G39: =E39-F39
B42: ÉPARGNE MENSUELLE | C42: Actuel | F42: Objectif | G42: Delta | H42: Pourcentage
C43: Lui | D43: Elle | E43: Foyer | F43: Goal | G43: ∆
B44: NON NÉGOCIABLE
B45: Épargne | C45: 1000 | D45: 2500 | E45: =C45+D45 | F45: 5500 | G45: =E45-F45
B46: TOTAL DE L'ÉPARGNE | C46: =SUM(C45) | D46: =SUM(D45) | E46: =C46+D46 | F46: =SUM(F45) | G46: =E46-F46 | H46: =PRODUCT(E46,1)/$E$38
B49: TOTAL ÉPARGNE MENSUELLE | C49: =C46 | D49: =D46 | E49: =E46 | F49: =F46 | G49: =E49-F49
B50: TOTAL ÉPARGNE ANNUELLE | C50: =PRODUCT(C49,12) | D50: =PRODUCT(D49,12) | E50: =PRODUCT(E49,12) | F50: =PRODUCT(F49,12) | G50: =E50-F50
B53: DÉPENSES MENSUELLES | C53: Actuel | F53: Objectif | G53: Delta | H53: Pourcentage
C54: Lui | D54: Elle | E54: Foyer | F54: Goal | G54: ∆
B55: SURVIE
B56: Alimentation : Courses | C56: 300 | D56: 250 | E56: =C56+D56 | G56: =E56-F56
B57: Frais bancaires | C57: 20 | D57: 20 | E57: =C57+D57 | G57: =E57-F57
B58: Impôt sur les revenus | D58: 50 | E58: =C58+D58 | G58: =E58-F58
B59: Résidence principale : Assurance habitation | D59: 20 | E59: =C59+D59 | G59: =E59-F59
B60: Résidence principale : Charges de copro/lotissement | D60: 80 | E60: =C60+D60 | G60: =E60-F60
B61: Résidence principale : Eau | D61: 50 | E61: =C61+D61 | G61: =E61-F61
B62: Résidence principale : Électricité | D62: 50 | E62: =C62+D62 | G62: =E62-F62
B63: Résidence principale : Gaz | D63: 50 | E63: =C63+D63 | G63: =E63-F63
B64: Résidence principale : Loyer ou mensualité | C64: 1500 | E64: =C64+D64 | G64: =E64-F64
B65: Résidence principale : Taxe foncière | C65: 1200 | E65: =C65+D65 | G65: =E65-F65
B66: Autres dépenses | E66: =C66+D66 | G66: =E66-F66
B67: TOTAL DES DÉPENSES SURVIE | C67: =SUM(C56:C66) | D67: =SUM(D56:D66) | E67: =C67+D67 | F67: =SUM(F56:F66) | G67: =E67-F67 | H67: =PRODUCT(E67,1)/$E$38
B69: ESSENTIEL
B70: Abonnement téléphone | C70: 25 | D70: 20 | E70: =C70+D70 | G70: =E70-F70
B71: Animaux | E71: =C71+D71 | G71: =E71-F71
B72: Crèche/garderie/nounou | E72: =C72+D72 | G72: =E72-F72
B73: Résidence principale : Abonnement câble/Netflix | C73: 20 | E73: =C73+D73 | G73: =E73-F73
B74: Résidence principale : Abonnement internet | C74: 20 | E74: =C74+D74 | G74: =E74-F74
B75: Résidence principale : Réparations | D75: 10 | E75: =C75+D75 | G75: =E75-F75
B76: Investissements immobiliers : Assurance emprunteur | E76: =C76+D76 | G76: =E76-F76
B77: Investissements immobiliers : Assurance PNO | C77: 10 | E77: =C77+D77 | G77: =E77-F77
B78: Investissements immobiliers : Charges de copro/loti | D78: 80 | E78: =C78+D78 | G78: =E78-F78
B79: Investissements immobiliers : CFE | C79: 40 | E79: =C79+D79 | G79: =E79-F79
B80: Investissements immobiliers : Eau/électricité/gaz | D80: 35 | E80: =C80+D80 | G80: =E80-F80
B81: Investissements immobiliers : Frais de gestion | C81: 45 | E81: =C81+D81 | G81: =E81-F81
B82: Investissements immobiliers : Mensualité de crédit | C82: 500 | D82: 500 | E82: =C82+D82 | G82: =E82-F82
B83: Investissements immobiliers : Taxe foncière | C83: 50 | D83: 50 | E83: =C83+D83 | G83: =E83-F83
B84: Investissements immobiliers : Travaux/réparations | D84: 100 | E84: =C84+D84 | G84: =E84-F84
B85: Mutuelle | E85: =C85+D85 | G85: =E85-F85
B86: Assurance auto/moto | E86: =C86+D86 | G86: =E86-F86
B87: Assurance vie / décès | E87: =C87+D87 | G87: =E87-F87
B88: Prévoyance | E88: =C88+D88 | G88: =E88-F88
B89: Transport : Essence | C89: 200 | D89: 50 | E89: =C89+D89 | G89: =E89-F89
B90: Transport : Parking | E90: =C90+D90 | G90: =E90-F90
B91: Transport : Crédit/LOA | C91: 150 | D91: 50 | E91: =C91+D91 | G91: =E91-F91
B92: Transport : Abonnement | E92: =C92+D92 | G92: =E92-F92
B93: Autres dépenses | E93: =C93+D93 | G93: =E93-F93
B94: TOTAL DES DÉPENSES ESSENTIELLES | C94: =SUM(C70:C93) | D94: =SUM(D70:D93) | E94: =C94+D94 | F94: =SUM(F70:F93) | G94: =E94-F94 | H94: =PRODUCT(E94,1)/$E$38
B96: CONFORT
B97: Abonnement salle de sport | E97: =C97+D97 | G97: =E97-F97
B98: Activité / sorties | E98: =C98+D98 | G98: =E98-F98
B99: Alimentation : Restaurant | C99: 100 | D99: 50 | E99: =C99+D99 | G99: =E99-F99
B100: Cadeaux | C100: 20 | E100: =C100+D100 | G100: =E100-F100
B101: Éducation / Formation | E101: =C101+D101 | G101: =E101-F101
B102: Garde-robe | D102: 150 | E102: =C102+D102 | G102: =E102-F102
B103: Loisirs / Hobbies | E103: =C103+D103 | G103: =E103-F103
B104: Vacances | E104: =C104+D104 | G104: =E104-F104
B105: Bien-être / Santé | E105: =C105+D105 | G105: =E105-F105
B106: Autres dépenses | E106: =C106+D106 | G106: =E106-F106
B107: TOTAL DES DÉPENSES CONFORT | C107: =SUM(C97:C106) | D107: =SUM(D97:D106) | E107: =C107+D107 | F107: =SUM(F97:F106) | G107: =E107-F107 | H107: =PRODUCT(E107,1)/$E$38
B109: DONS
B110: Association | E110: =C110+D110 | G110: =E110-F110
B111: Impôt / Zakat | E111: =C111+D111 | G111: =E111-F111
B112: Église / Mosquée / Synagogue | E112: =C112+D112 | G112: =E112-F112
B113: Autres dons | E113: =C113+D113 | G113: =E113-F113
B114: TOTAL DES DONS | C114: =SUM(C110:C113) | D114: =SUM(D110:D113) | E114: =C114+D114 | F114: =SUM(F110:F113) | G114: =E114-F114 | H114: =PRODUCT(E114,1)/$E$38
B116: ENFANTS
B117: Scolarité | E117: =C117+D117 | G117: =E117-F117
B118: Activités | E118: =C118+D118 | G118: =E118-F118
B119: Autres | E119: =C119+D119 | G119: =E119-F119
...

Sheet Bilan
B2: Emeline SIRON | G2: ANNÉE : | H2: 2025
B3: Bilan
B5: PATRIMOINE | C5: Actuel | F5: Objectif | G5: Delta
C6: Lui | D6: Elle | E6: Foyer | F6: Goal | G6: ∆
B8: Total Actif | C8: =C103 | D8: =D103 | E8: =E103 | F8: =F103 | G8: =G103
B9: Total Passif | C9: =C130 | D9: =D130 | E9: =E130 | F9: =F130 | G9: =G130
B11: TOTAL PATRIMOINE NET | C11: =C8-C9 | D11: =D8-D9 | E11: =E8-E9 | F11: =F8-F9 | G11: =E11-F11
B14: ACTIF | C14: Actuel | F14: Objectif | G14: Delta | H14: Pourcentage
C15: Lui | D15: Elle | E15: Foyer | F15: Goal | G15: ∆
B16: LIQUIDITÉ
B17: Compte courant | C17: 300000 | E17: =C17+D17 | F17: 550000 | G17: =E17-F17
B18: Livret A | E18: =C18+D18 | G18: =E18-F18
B19: LDDS | E19: =C19+D19 | G19: =E19-F19
B20: LEP | E20: =C20+D20 | G20: =E20-F20
B21: Livret Jeune | E21: =C21+D21 | G21: =E21-F21
B22: CEL | E22: =C22+D22 | G22: =E22-F22
B23: PEL | E23: =C23+D23 | G23: =E23-F23
B24: PERP | E24: =C24+D24 | G24: =E24-F24
B25: Compte à terme CAT | E25: =C25+D25 | G25: =E25-F25
B26: Compte Sur Livret CSL | E26: =C26+D26 | G26: =E26-F26
B27: Autre | E27: =C27+D27 | G27: =E27-F27
B28: TOTAL LIQUIDITÉ | C28: =SUM(C17:C27) | D28: =SUM(D17:D27) | E28: =C28+D28 | F28: =SUM(F17:F27) | G28: =E28-F28 | H28: =PRODUCT(E28,1)/$E$103
B30: IMMOBILIER
B31: Terrain | C31: 400000 | E31: =C31+D31 | G31: =E31-F31
B32: Appartement | E32: =C32+D32 | G32: =E32-F32
B33: Immeuble | E33: =C33+D33 | G33: =E33-F33
B34: Maison | E34: =C34+D34 | G34: =E34-F34
B35: Commerce | E35: =C35+D35 | G35: =E35-F35
B36: Bureau | E36: =C36+D36 | G36: =E36-F36
B37: Entrepôt | E37: =C37+D37 | G37: =E37-F37
B38: Parking | E38: =C38+D38 | G38: =E38-F38
B39: Cave | E39: =C39+D39 | G39: =E39-F39
B40: Autre | E40: =C40+D40 | G40: =E40-F40
B41: TOTAL IMMOBILIER | C41: =SUM(C31:C40) | D41: =SUM(D31:D40) | E41: =C41+D41 | F41: =SUM(F31:F40) | G41: =E41-F41 | H41: =PRODUCT(E41,1)/$E$103
B43: BOURSE
B44: Action | C44: 250000 | E44: =C44+D44 | F44: 225000 | G44: =E44-F44
B45: Obligation | E45: =C45+D45 | G45: =E45-F45
B46: ETF | E46: =C46+D46 | G46: =E46-F46
B47: SICAV | E47: =C47+D47 | G47: =E47-F47
B48: FCP | E48: =C48+D48 | G48: =E48-F48
B49: Warrant | E49: =C49+D49 | G49: =E49-F49
B50: Option | E50: =C50+D50 | G50: =E50-F50
B51: Stock-option | E51: =C51+D51 | G51: =E51-F51
B52: CFD | E52: =C52+D52 | G52: =E52-F52
B53: Future | E53: =C53+D53 | G53: =E53-F53
B54: Autre | E54: =C54+D54 | G54: =E54-F54
B55: TOTAL BOURSE | C55: =SUM(C44:C54) | D55: =SUM(D44:D54) | E55: =C55+D55 | F55: =SUM(F44:F54) | G55: =E55-F55 | H55: =PRODUCT(E55,1)/$E$103
B57: CRYPTOMONNAIE
B58: Majeure | C58: 180000 | E58: =C58+D58 | F58: 150000 | G58: =E58-F58
B59: Alternative coin | E59: =C59+D59 | G59: =E59-F59
B60: NFT coin | E60: =C60+D60 | G60: =E60-F60
B61: DEFI coin | E61: =C61+D61 | G61: =E61-F61
B62: METAVERSE coin | E62: =C62+D62 | G62: =E62-F62
B63: Stable coin | E63: =C63+D63 | G63: =E63-F63
B64: Fiat | E64: =C64+D64 | G64: =E64-F64
B65: Autre | E65: =C65+D65 | G65: =E65-F65
B66: TOTAL CRYPTOMONNAIE | C66: =SUM(C58:C65) | D66: =SUM(D58:D65) | E66: =C66+D66 | F66: =SUM(F58:F65) | G66: =E66-F66 | H66: =PRODUCT(E66,1)/$E$103
B68: PRIVATE EQUITY
B69: Capital innovation | C69: 100000 | E69: =C69+D69 | F69: 100000 | G69: =E69-F69
B70: Capital développement | E70: =C70+D70 | G70: =E70-F70
B71: Capital retournement | E71: =C71+D71 | G71: =E71-F71
B72: Capital transmission | E72: =C72+D72 | G72: =E72-F72
B73: Autre | E73: =C73+D73 | G73: =E73-F73
B74: TOTAL PRIVATE EQUITY | C74: =SUM(C69:C73) | D74: =SUM(D69:D73) | E74: =C74+D74 | F74: =SUM(F69:F73) | G74: =E74-F74 | H74: =PRODUCT(E74,1)/$E$103
B76: CROWDFUNDING
B77: Immobilier | E77: =C77+D77 | F77: 5000 | G77: =E77-F77
B78: Entreprise | E78: =C78+D78 | G78: =E78-F78
B79: Particulier | E79: =C79+D79 | G79: =E79-F79
B80: Autre | E80: =C80+D80 | G80: =E80-F80
B81: TOTAL CROWDFUNDING | C81: =SUM(C77:C80) | D81: =SUM(D77:D80) | E81: =C81+D81 | F81: =SUM(F77:F80) | G81: =E81-F81 | H81: =PRODUCT(E81,1)/$E$103
B83: MATIÈRES PREMIÈRES
B84: Or | D84: 50000 | E84: =C84+D84 | F84: 100000 | G84: =E84-F84
B85: Argent | E85: =C85+D85 | G85: =E85-F85
B86: Monnaies | E86: =C86+D86 | G86: =E86-F86
B87: Vin / Whisky | E87: =C87+D87 | G87: =E87-F87
B88: Art | E88: =C88+D88 | G88: =E88-F88
B89: Bijoux / Montres | E89: =C89+D89 | G89: =E89-F89
B90: Véhicule | E90: =C90+D90 | G90: =E90-F90
B91: Autre | E91: =C91+D91 | G91: =E91-F91
B92: TOTAL MATIÈRES PREMIÈRES | C92: =SUM(C84:C91) | D92: =SUM(D84:D91) | E92: =C92+D92 | F92: =SUM(F84:F91) | G92: =E92-F92 | H92: =PRODUCT(E92,1)/$E$103
B94: ENTREPRISE
B95: SCI | E95: =C95+D95 | G95: =E95-F95
B96: SAS | E96: =C96+D96 | G96: =E96-F96
B97: SARL | E97: =C97+D97 | G97: =E97-F97
B98: Micro-entreprise | E98: =C98+D98 | G98: =E98-F98
B99: Autre | E99: =C99+D99 | G99: =E99-F99
B100: TOTAL ENTREPRISE | C100: =SUM(C95:C99) | D100: =SUM(D95:D99) | E100: =C100+D100 | F100: =SUM(F95:F99) | G100: =E100-F100 | H100: =PRODUCT(E100,1)/$E$103
B103: TOTAL ACTIF | C103: =C28+C41+C55+C66+C74+C81+C92+C100 | D103: =D28+D41+D55+D66+D74+D81+D92+D100 | E103: =E28+E41+E55+E66+E74+E81+E92+E100 | F103: =F28+F41+F55+F66+F74+F81+F92+F100 | G103: =E103-F103
B106: PASSIF | C106: Actuel | F106: Objectif | G106: Delta | H106: Pourcentage
C107: Lui | D107: Elle | E107: Foyer | F107: Goal | G107: ∆
B108: DETTES
B109: Résidence principale : Capital restant dû | C109: 100 | E109: =C109+D109 | G109: =E109-F109
B110: Investissements immo : Capital restant dû | D110: 350000 | E110: =C110+D110 | G110: =E110-F110
B111: Crédit auto | E111: =C111+D111 | G111: =E111-F111
B112: Crédit consommation | E112: =C112+D112 | G112: =E112-F112
B113: Prêt familial | E113: =C113+D113 | G113: =E113-F113
B114: Découvert | E114: =C114+D114 | G114: =E114-F114
B115: Autre dette | E115: =C115+D115 | G115: =E115-F115
B116: TOTAL DETTES IMMOBILIÈRES | C116: =SUM(C109:C110) | D116: =SUM(D109:D110) | E116: =C116+D116 | F116: =SUM(F109:F110) | G116: =E116-F116
B117: TOTAL AUTRES DETTES | C117: =SUM(C111:C115) | D117: =SUM(D111:D115) | E117: =C117+D117 | F117: =SUM(F111:F115) | G117: =E117-F117
...

Sheet Croissance
C2: Croissance
B5: ÉVOLUTION AU COURS DES ANNÉES | C5: ÉVOLUTION AU COURS DES ANNÉES
C7: Année | D7: Revenus actifs | E7: Revenus passifs | F7: Total des revenus | H7: Liquidité | I7: Immobilier | J7: Bourse | K7: Cryptomonnaie | L7: Private Equity | M7: Autre | N7: Patrimoine brut | P7: Patrimoine net
C8: A-4 | D8: 1500 | E8: 5000 | F8: =E8+D8 | H8: 50000 | N8: =SUM(H8:M8)
C9: A-3 | D9: 3000 | E9: 10000 | F9: =E9+D9 | H9: 100000 | N9: =SUM(H9:M9)
C10: A-2 | D10: 11000 | E10: 15000 | F10: =E10+D10 | H10: 200000 | N10: =SUM(H10:M10)
C11: A-1 | D11: 25000 | E11: 25000 | F11: =E11+D11 | H11: 250000 | N11: =SUM(H11:M11)
C12: En cours | D12: =PRODUCT('Compte de résultats'!E25,12) | E12: =PRODUCT('Compte de résultats'!E35,12) | F12: =E12+D12 | H12: =Bilan!E28 | I12: =Bilan!E41 | J12: =Bilan!E55 | K12: =Bilan!E66 | L12: =Bilan!E74 | M12: =Bilan!E81+Bilan!E92+Bilan!E100 | N12: =SUM(H12:M12) | P12: =Bilan!E11
C17: CROISSANCE DES REVENUS | J17: CROISSANCE DU PATRIMOINE BRUT
C46: CROISSANCE DU PATRIMOINE NET

Sheet Objectifs
B2: Objectifs
B5: ACTIONS | C5: STATUS
B6: Générer un SMIC mensuel de revenus passifs | C6: À faire
B7: Générer 2 500 € mensuel de revenus passifs | C7: À faire
B8: Générer 5 000 € mensuel de revenus passifs | C8: En cours
B9: Générer 10 000 € mensuel de revenus passifs | C9: À faire
B10: Générer un SMIC mensuel de cash-flow net avec l'immobilier | C10: Fait
B11: Générer 2 500 € mensuel de cash-flow net avec l'immobilier | C11: À faire
B12: Générer 5 000 € mensuel de cash-flow net avec l'immobilier | C12: À faire
B13: Générer 100 € mensuel de dividendes | C13: Fait
B14: Générer 500 € mensuel de dividendes | C14: À faire
B15: Générer 2 000 € mensuel de dividendes | C15: À faire
B16: Générer 100 € mensuel avec le trading | C16: À faire
... B38: Détenir 5 000 000 € de patrimoine net | C38: À faire

Sheet Graphiques
B2: À NE PAS TOUCHER !
B5: Graphiques

Sheet Pivots
B2: À NE PAS TOUCHER !
C4: Revenus
C5: Autre | D5: ='Compte de résultats'!E24+'Compte de résultats'!E34
C6: Crowdfunding | D6: ='Compte de résultats'!E33
C7: Private Equity | D7: ='Compte de résultats'!E32
C8: Bourse | D8: =SUM('Compte de résultats'!E30:E31)
C9: Immobilier | D9: =SUM('Compte de résultats'!E28:E29)
C10: Travail | D10: =SUM('Compte de résultats'!E18:E23)
E12: Dépenses
E13: Autre | F13: ='Compte de résultats'!E122-F18-F17-F16-F15-F14
E14: Plaisir | F14: =SUM('Compte de résultats'!E98:E106)+'Compte de résultats'!E111+'Compte de résultats'!E112+'Compte de résultats'!E113+'Compte de résultats'!E116
E15: Voiture | F15: =SUM('Compte de résultats'!E91:E93)
E16: Alimentation | F16: ='Compte de résultats'!E56
E17: Invest. locatif | F17: =SUM('Compte de résultats'!E76:E86)
E18: Rési. princip. | F18: =SUM('Compte de résultats'!E59:E65)+SUM('Compte de résultats'!E73:E75)
G20: Épargne VS Dépenses
G21: Épargne | H21: Dépenses
G22: ='Compte de résultats'!E49 | H22: ='Compte de résultats'!E122
I24: Dépenses par catégorie
I25: Autre | J25: =F13/SUM($F$13:$F$18)
I26: Plaisir | J26: =F14/SUM($F$13:$F$18)
I27: Voiture | J27: =F15/SUM($F$13:$F$18)
I28: Alimentation | J28: =F16/SUM($F$13:$F$18)
I29: Invest. locatif | J29: =F17/SUM($F$13:$F$18)
I30: Rési. princip. | J30: =F18/SUM($F$13:$F$18)
K32: Taux d'épargne
K33: Épargne | L33: Objectif
K34: ='Compte de résultats'!H46
M36: Patrimoine
M37: Brut | N37: Net
M38: =Bilan!E103 | N38: =Bilan!E11
O42: Objectif revenus
O43: Actuel | P43: Objectif
O44: ='Compte de résultats'!E39 | P44: ='Compte de résultats'!F39
Q48: Objectif patrimoine net
Q49: Actuel | R49: Objectif
Q50: =Bilan!E11 | R50: =Bilan!F11
S54: Objectif revenus reste
S55: Actuel | T55: Objectif
S56: =O44 | T56: =P44-O44
U60: Objectif patrimoine reste
U61: Actuel | V61: Objectif
U62: =Q50 | V62: =R50-Q50
