Workbook

Sheet Simulateur Amortissement
A1: SIMULATEUR TABLEAU D'AMORTISSEMENT
A2: La méthode Emeline SIRON — Cases jaunes = à modifier | Cases vertes = résultats automatiques
A4: PARAMÈTRES DU CRÉDIT
A5: Montant emprunté | B5: 200000
A6: Taux d'intérêt annuel | B6: 0.035
A7: Durée (années) | B7: 20
A8: Taux assurance annuel | B8: 0.003
A9: Différé (mois) | B9: 0
A11: RÉSULTATS SYNTHÈSE
A12: Mensualité crédit (hors assurance) | B12: =-PMT(B6/12,B7*12,B5)
A13: Mensualité assurance | B13: =B5*B8/12
A14: MENSUALITÉ TOTALE | B14: =B12+B13
A15: Total intérêts payés | B15: =B12*B7*12-B5
A16: Total assurance payée | B16: =B13*B7*12
A17: COÛT TOTAL DU CRÉDIT | B17: =B15+B16
A18: Coût total de l'opération | B18: =B5+B17

Sheet Tableau Amortissement
A1: TABLEAU D'AMORTISSEMENT DÉTAILLÉ
A3: Mois | B3: Mensualité | C3: Intérêts | D3: Capital amorti | E3: Assurance | F3: Total payé | G3: Capital restant dû
A4: 1 | B4: =IF(A4>'Simulateur Amortissement'!B7*12,"",'Simulateur Amortissement'!B12) | C4: ='Simulateur Amortissement'!B5*'Simulateur Amortissement'!B6/12 | D4: =IF(B4="","",B4-C4) | E4: =IF(A4>'Simulateur Amortissement'!B7*12,"",'Simulateur Amortissement'!B13) | F4: =IF(B4="","",B4+E4) | G4: ='Simulateur Amortissement'!B5-D4
A5: 2 | B5: =IF(A5>'Simulateur Amortissement'!B7*12,"",'Simulateur Amortissement'!B12) | C5: =G4*'Simulateur Amortissement'!B6/12 | D5: =IF(B5="","",B5-C5) | E5: =IF(A5>'Simulateur Amortissement'!B7*12,"",'Simulateur Amortissement'!B13) | F5: =IF(B5="","",B5+E5) | G5: =G4-D5
A6: 3 | B6: =IF(A6>'Simulateur Amortissement'!B7*12,"",'Simulateur Amortissement'!B12) | C6: =G5*'Simulateur Amortissement'!B6/12 | D6: =IF(B6="","",B6-C6) | E6: =IF(A6>'Simulateur Amortissement'!B7*12,"",'Simulateur Amortissement'!B13) | F6: =IF(B6="","",B6+E6) | G6: =G5-D6
A7: 4 | B7: =IF(A7>'Simulateur Amortissement'!B7*12,"",'Simulateur Amortissement'!B12) | C7: =G6*'Simulateur Amortissement'!B6/12 | D7: =IF(B7="","",B7-C7) | E7: =IF(A7>'Simulateur Amortissement'!B7*12,"",'Simulateur Amortissement'!B13) | F7: =IF(B7="","",B7+E7) | G7: =G6-D7
A8: 5 | B8: =IF(A8>'Simulateur Amortissement'!B7*12,"",'Simulateur Amortissement'!B12) | C8: =G7*'Simulateur Amortissement'!B6/12 | D8: =IF(B8="","",B8-C8) | E8: =IF(A8>'Simulateur Amortissement'!B7*12,"",'Simulateur Amortissement'!B13) | F8: =IF(B8="","",B8+E8) | G8: =G7-D8
A9: 6 | B9: =IF(A9>'Simulateur Amortissement'!B7*12,"",'Simulateur Amortissement'!B12) | C9: =G8*'Simulateur Amortissement'!B6/12 | D9: =IF(B9="","",B9-C9) | E9: =IF(A9>'Simulateur Amortissement'!B7*12,"",'Simulateur Amortissement'!B13) | F9: =IF(B9="","",B9+E9) | G9: =G8-D9
A10: 7 | B10: =IF(A10>'Simulateur Amortissement'!B7*12,"",'Simulateur Amortissement'!B12) | C10: =G9*'Simulateur Amortissement'!B6/12 | D10: =IF(B10="","",B10-C10) | E10: =IF(A10>'Simulateur Amortissement'!B7*12,"",'Simulateur Amortissement'!B13) | F10: =IF(B10="","",B10+E10) | G10: =G9-D10
A11: 8 | B11: =IF(A11>'Simulateur Amortissement'!B7*12,"",'Simulateur Amortissement'!B12) | C11: =G10*'Simulateur Amortissement'!B6/12 | D11: =IF(B11="","",B11-C11) | E11: =IF(A11>'Simulateur Amortissement'!B7*12,"",'Simulateur Amortissement'!B13) | F11: =IF(B11="","",B11+E11) | G11: =G10-D11
A12: 9 | B12: =IF(A12>'Simulateur Amortissement'!B7*12,"",'Simulateur Amortissement'!B12) | C12: =G11*'Simulateur Amortissement'!B6/12 | D12: =IF(B12="","",B12-C12) | E12: =IF(A12>'Simulateur Amortissement'!B7*12,"",'Simulateur Amortissement'!B13) | F12: =IF(B12="","",B12+E12) | G12: =G11-D12
A13: 10 | B13: =IF(A13>'Simulateur Amortissement'!B7*12,"",'Simulateur Amortissement'!B12) | C13: =G12*'Simulateur Amortissement'!B6/12 | D13: =IF(B13="","",B13-C13) | E13: =IF(A13>'Simulateur Amortissement'!B7*12,"",'Simulateur Amortissement'!B13) | F13: =IF(B13="","",B13+E13) | G13: =G12-D13
A14: 11 | B14: =IF(A14>'Simulateur Amortissement'!B7*12,"",'Simulateur Amortissement'!B12) | C14: =G13*'Simulateur Amortissement'!B6/12 | D14: =IF(B14="","",B14-C14) | E14: =IF(A14>'Simulateur Amortissement'!B7*12,"",'Simulateur Amortissement'!B13) | F14: =IF(B14="","",B14+E14) | G14: =G13-D14
A15: 12 | B15: =IF(A15>'Simulateur Amortissement'!B7*12,"",'Simulateur Amortissement'!B12) | C15: =G14*'Simulateur Amortissement'!B6/12 | D15: =IF(B15="","",B15-C15) | E15: =IF(A15>'Simulateur Amortissement'!B7*12,"",'Simulateur Amortissement'!B13) | F15: =IF(B15="","",B15+E15) | G15: =G14-D15
A16: 13 | B16: =IF(A16>'Simulateur Amortissement'!B7*12,"",'Simulateur Amortissement'!B12) | C16: =G15*'Simulateur Amortissement'!B6/12 | D16: =IF(B16="","",B16-C16) | E16: =IF(A16>'Simulateur Amortissement'!B7*12,"",'Simulateur Amortissement'!B13) | F16: =IF(B16="","",B16+E16) | G16: =G15-D16
A17: 14 | B17: =IF(A17>'Simulateur Amortissement'!B7*12,"",'Simulateur Amortissement'!B12) | C17: =G16*'Simulateur Amortissement'!B6/12 | D17: =IF(B17="","",B17-C17) | E17: =IF(A17>'Simulateur Amortissement'!B7*12,"",'Simulateur Amortissement'!B13) | F17: =IF(B17="","",B17+E17) | G17: =G16-D17
A18: 15 | B18: =IF(A18>'Simulateur Amortissement'!B7*12,"",'Simulateur Amortissement'!B12) | C18: =G17*'Simulateur Amortissement'!B6/12 | D18: =IF(B18="","",B18-C18) | E18: =IF(A18>'Simulateur Amortissement'!B7*12,"",'Simulateur Amortissement'!B13) | F18: =IF(B18="","",B18+E18) | G18: =G17-D18
A19: 16 | B19: =IF(A19>'Simulateur Amortissement'!B7*12,"",'Simulateur Amortissement'!B12) | C19: =G18*'Simulateur Amortissement'!B6/12 | D19: =IF(B19="","",B19-C19) | E19: =IF(A19>'Simulateur Amortissement'!B7*12,"",'Simulateur Amortissement'!B13) | F19: =IF(B19="","",B19+E19) | G19: =G18-D19
A20: 17 | B20: =IF(A20>'Simulateur Amortissement'!B7*12,"",'Simulateur Amortissement'!B12) | C20: =G19*'Simulateur Amortissement'!B6/12 | D20: =IF(B20="","",B20-C20) | E20: =IF(A20>'Simulateur Amortissement'!B7*12,"",'Simulateur Amortissement'!B13) | F20: =IF(B20="","",B20+E20) | G20: =G19-D20
A21: 18 | B21: =IF(A21>'Simulateur Amortissement'!B7*12,"",'Simulateur Amortissement'!B12) | C21: =G20*'Simulateur Amortissement'!B6/12 | D21: =IF(B21="","",B21-C21) | E21: =IF(A21>'Simulateur Amortissement'!B7*12,"",'Simulateur Amortissement'!B13) | F21: =IF(B21="","",B21+E21) | G21: =G20-D21
A22: 19 | B22: =IF(A22>'Simulateur Amortissement'!B7*12,"",'Simulateur Amortissement'!B12) | C22: =G21*'Simulateur Amortissement'!B6/12 | D22: =IF(B22="","",B22-C22) | E22: =IF(A22>'Simulateur Amortissement'!B7*12,"",'Simulateur Amortissement'!B13) | F22: =IF(B22="","",B22+E22) | G22: =G21-D22
A23: 20 | B23: =IF(A23>'Simulateur Amortissement'!B7*12,"",'Simulateur Amortissement'!B12) | C23: =G22*'Simulateur Amortissement'!B6/12 | D23: =IF(B23="","",B23-C23) | E23: =IF(A23>'Simulateur Amortissement'!B7*12,"",'Simulateur Amortissement'!B13) | F23: =IF(B23="","",B23+E23) | G23: =G22-D23
A24: 21 | B24: =IF(A24>'Simulateur Amortissement'!B7*12,"",'Simulateur Amortissement'!B12) | C24: =G23*'Simulateur Amortissement'!B6/12 | D24: =IF(B24="","",B24-C24) | E24: =IF(A24>'Simulateur Amortissement'!B7*12,"",'Simulateur Amortissement'!B13) | F24: =IF(B24="","",B24+E24) | G24: =G23-D24
A25: 22 | B25: =IF(A25>'Simulateur Amortissement'!B7*12,"",'Simulateur Amortissement'!B12) | C25: =G24*'Simulateur Amortissement'!B6/12 | D25: =IF(B25="","",B25-C25) | E25: =IF(A25>'Simulateur Amortissement'!B7*12,"",'Simulateur Amortissement'!B13) | F25: =IF(B25="","",B25+E25) | G25: =G24-D25
A26: 23 | B26: =IF(A26>'Simulateur Amortissement'!B7*12,"",'Simulateur Amortissement'!B12) | C26: =G25*'Simulateur Amortissement'!B6/12 | D26: =IF(B26="","",B26-C26) | E26: =IF(A26>'Simulateur Amortissement'!B7*12,"",'Simulateur Amortissement'!B13) | F26: =IF(B26="","",B26+E26) | G26: =G25-D26
A27: 24 | B27: =IF(A27>'Simulateur Amortissement'!B7*12,"",'Simulateur Amortissement'!B12) | C27: =G26*'Simulateur Amortissement'!B6/12 | D27: =IF(B27="","",B27-C27) | E27: =IF(A27>'Simulateur Amortissement'!B7*12,"",'Simulateur Amortissement'!B13) | F27: =IF(B27="","",B27+E27) | G27: =G26-D27
A28: 25 | B28: =IF(A28>'Simulateur Amortissement'!B7*12,"",'Simulateur Amortissement'!B12) | C28: =G27*'Simulateur Amortissement'!B6/12 | D28: =IF(B28="","",B28-C28) | E28: =IF(A28>'Simulateur Amortissement'!B7*12,"",'Simulateur Amortissement'!B13) | F28: =IF(B28="","",B28+E28) | G28: =G27-D28
A29: 26 | B29: =IF(A29>'Simulateur Amortissement'!B7*12,"",'Simulateur Amortissement'!B12) | C29: =G28*'Simulateur Amortissement'!B6/12 | D29: =IF(B29="","",B29-C29) | E29: =IF(A29>'Simulateur Amortissement'!B7*12,"",'Simulateur Amortissement'!B13) | F29: =IF(B29="","",B29+E29) | G29: =G28-D29
A30: 27 | B30: =IF(A30>'Simulateur Amortissement'!B7*12,"",'Simulateur Amortissement'!B12) | C30: =G29*'Simulateur Amortissement'!B6/12 | D30: =IF(B30="","",B30-C30) | E30: =IF(A30>'Simulateur Amortissement'!B7*12,"",'Simulateur Amortissement'!B13) | F30: =IF(B30="","",B30+E30) | G30: =G29-D30
A31: 28 | B31: =IF(A31>'Simulateur Amortissement'!B7*12,"",'Simulateur Amortissement'!B12) | C31: =G30*'Simulateur Amortissement'!B6/12 | D31: =IF(B31="","",B31-C31) | E31: =IF(A31>'Simulateur Amortissement'!B7*12,"",'Simulateur Amortissement'!B13) | F31: =IF(B31="","",B31+E31) | G31: =G30-D31
A32: 29 | B32: =IF(A32>'Simulateur Amortissement'!B7*12,"",'Simulateur Amortissement'!B12) | C32: =G31*'Simulateur Amortissement'!B6/12 | D32: =IF(B32="","",B32-C32) | E32: =IF(A32>'Simulateur Amortissement'!B7*12,"",'Simulateur Amortissement'!B13) | F32: =IF(B32="","",B32+E32) | G32: =G31-D32
A33: 30 | B33: =IF(A33>'Simulateur Amortissement'!B7*12,"",'Simulateur Amortissement'!B12) | C33: =G32*'Simulateur Amortissement'!B6/12 | D33: =IF(B33="","",B33-C33) | E33: =IF(A33>'Simulateur Amortissement'!B7*12,"",'Simulateur Amortissement'!B13) | F33: =IF(B33="","",B33+E33) | G33: =G32-D33
A34: 31 | B34: =IF(A34>'Simulateur Amortissement'!B7*12,"",'Simulateur Amortissement'!B12) | C34: =G33*'Simulateur Amortissement'!B6/12 | D34: =IF(B34="","",B34-C34) | E34: =IF(A34>'Simulateur Amortissement'!B7*12,"",'Simulateur Amortissement'!B13) | F34: =IF(B34="","",B34+E34) | G34: =G33-D34
A35: 32 | B35: =IF(A35>'Simulateur Amortissement'!B7*12,"",'Simulateur Amortissement'!B12) | C35: =G34*'Simulateur Amortissement'!B6/12 | D35: =IF(B35="","",B35-C35) | E35: =IF(A35>'Simulateur Amortissement'!B7*12,"",'Simulateur Amortissement'!B13) | F35: =IF(B35="","",B35+E35) | G35: =G34-D35
A36: 33 | B36: =IF(A36>'Simulateur Amortissement'!B7*12,"",'Simulateur Amortissement'!B12) | C36: =G35*'Simulateur Amortissement'!B6/12 | D36: =IF(B36="","",B36-C36) | E36: =IF(A36>'Simulateur Amortissement'!B7*12,"",'Simulateur Amortissement'!B13) | F36: =IF(B36="","",B36+E36) | G36: =G35-D36
A37: 34 | B37: =IF(A37>'Simulateur Amortissement'!B7*12,"",'Simulateur Amortissement'!B12) | C37: =G36*'Simulateur Amortissement'!B6/12 | D37: =IF(B37="","",B37-C37) | E37: =IF(A37>'Simulateur Amortissement'!B7*12,"",'Simulateur Amortissement'!B13) | F37: =IF(B37="","",B37+E37) | G37: =G36-D37
A38: 35 | B38: =IF(A38>'Simulateur Amortissement'!B7*12,"",'Simulateur Amortissement'!B12) | C38: =G37*'Simulateur Amortissement'!B6/12 | D38: =IF(B38="","",B38-C38) | E38: =IF(A38>'Simulateur Amortissement'!B7*12,"",'Simulateur Amortissement'!B13) | F38: =IF(B38="","",B38+E38) | G38: =G37-D38
A39: 36 | B39: =IF(A39>'Simulateur Amortissement'!B7*12,"",'Simulateur Amortissement'!B12) | C39: =G38*'Simulateur Amortissement'!B6/12 | D39: =IF(B39="","",B39-C39) | E39: =IF(A39>'Simulateur Amortissement'!B7*12,"",'Simulateur Amortissement'!B13) | F39: =IF(B39="","",B39+E39) | G39: =G38-D39
A40: 37 | B40: =IF(A40>'Simulateur Amortissement'!B7*12,"",'Simulateur Amortissement'!B12) | C40: =G39*'Simulateur Amortissement'!B6/12 | D40: =IF(B40="","",B40-C40) | E40: =IF(A40>'Simulateur Amortissement'!B7*12,"",'Simulateur Amortissement'!B13) | F40: =IF(B40="","",B40+E40) | G40: =G39-D40
A41: 38 | B41: =IF(A41>'Simulateur Amortissement'!B7*12,"",'Simulateur Amortissement'!B12) | C41: =G40*'Simulateur Amortissement'!B6/12 | D41: =IF(B41="","",B41-C41) | E41: =IF(A41>'Simulateur Amortissement'!B7*12,"",'Simulateur Amortissement'!B13) | F41: =IF(B41="","",B41+E41) | G41: =G40-D41
A42: 39 | B42: =IF(A42>'Simulateur Amortissement'!B7*12,"",'Simulateur Amortissement'!B12) | C42: =G41*'Simulateur Amortissement'!B6/12 | D42: =IF(B42="","",B42-C42) | E42: =IF(A42>'Simulateur Amortissement'!B7*12,"",'Simulateur Amortissement'!B13) | F42: =IF(B42="","",B42+E42) | G42: =G41-D42
A43: 40 | B43: =IF(A43>'Simulateur Amortissement'!B7*12,"",'Simulateur Amortissement'!B12) | C43: =G42*'Simulateur Amortissement'!B6/12 | D43: =IF(B43="","",B43-C43) | E43: =IF(A43>'Simulateur Amortissement'!B7*12,"",'Simulateur Amortissement'!B13) | F43: =IF(B43="","",B43+E43) | G43: =G42-D43
A44: 41 | B44: =IF(A44>'Simulateur Amortissement'!B7*12,"",'Simulateur Amortissement'!B12) | C44: =G43*'Simulateur Amortissement'!B6/12 | D44: =IF(B44="","",B44-C44) | E44: =IF(A44>'Simulateur Amortissement'!B7*12,"",'Simulateur Amortissement'!B13) | F44: =IF(B44="","",B44+E44) | G44: =G43-D44
A45: 42 | B45: =IF(A45>'Simulateur Amortissement'!B7*12,"",'Simulateur Amortissement'!B12) | C45: =G44*'Simulateur Amortissement'!B6/12 | D45: =IF(B45="","",B45-C45) | E45: =IF(A45>'Simulateur Amortissement'!B7*12,"",'Simulateur Amortissement'!B13) | F45: =IF(B45="","",B45+E45) | G45: =G44-D45
A46: 43 | B46: =IF(A46>'Simulateur Amortissement'!B7*12,"",'Simulateur Amortissement'!B12) | C46: =G45*'Simulateur Amortissement'!B6/12 | D46: =IF(B46="","",B46-C46) | E46: =IF(A46>'Simulateur Amortissement'!B7*12,"",'Simulateur Amortissement'!B13) | F46: =IF(B46="","",B46+E46) | G46: =G45-D46
A47: 44 | B47: =IF(A47>'Simulateur Amortissement'!B7*12,"",'Simulateur Amortissement'!B12) | C47: =G46*'Simulateur Amortissement'!B6/12 | D47: =IF(B47="","",B47-C47) | E47: =IF(A47>'Simulateur Amortissement'!B7*12,"",'Simulateur Amortissement'!B13) | F47: =IF(B47="","",B47+E47) | G47: =G46-D47
A48: 45 | B48: =IF(A48>'Simulateur Amortissement'!B7*12,"",'Simulateur Amortissement'!B12) | C48: =G47*'Simulateur Amortissement'!B6/12 | D48: =IF(B48="","",B48-C48) | E48: =IF(A48>'Simulateur Amortissement'!B7*12,"",'Simulateur Amortissement'!B13) | F48: =IF(B48="","",B48+E48) | G48: =G47-D48
A49: 46 | B49: =IF(A49>'Simulateur Amortissement'!B7*12,"",'Simulateur Amortissement'!B12) | C49: =G48*'Simulateur Amortissement'!B6/12 | D49: =IF(B49="","",B49-C49) | E49: =IF(A49>'Simulateur Amortissement'!B7*12,"",'Simulateur Amortissement'!B13) | F49: =IF(B49="","",B49+E49) | G49: =G48-D49
A50: 47 | B50: =IF(A50>'Simulateur Amortissement'!B7*12,"",'Simulateur Amortissement'!B12) | C50: =G49*'Simulateur Amortissement'!B6/12 | D50: =IF(B50="","",B50-C50) | E50: =IF(A50>'Simulateur Amortissement'!B7*12,"",'Simulateur Amortissement'!B13) | F50: =IF(B50="","",B50+E50) | G50: =G49-D50
A51: 48 | B51: =IF(A51>'Simulateur Amortissement'!B7*12,"",'Simulateur Amortissement'!B12) | C51: =G50*'Simulateur Amortissement'!B6/12 | D51: =IF(B51="","",B51-C51) | E51: =IF(A51>'Simulateur Amortissement'!B7*12,"",'Simulateur Amortissement'!B13) | F51: =IF(B51="","",B51+E51) | G51: =G50-D51
A52: 49 | B52: =IF(A52>'Simulateur Amortissement'!B7*12,"",'Simulateur Amortissement'!B12) | C52: =G51*'Simulateur Amortissement'!B6/12 | D52: =IF(B52="","",B52-C52) | E52: =IF(A52>'Simulateur Amortissement'!B7*12,"",'Simulateur Amortissement'!B13) | F52: =IF(B52="","",B52+E52) | G52: =G51-D52
A53: 50 | B53: =IF(A53>'Simulateur Amortissement'!B7*12,"",'Simulateur Amortissement'!B12) | C53: =G52*'Simulateur Amortissement'!B6/12 | D53: =IF(B53="","",B53-C53) | E53: =IF(A53>'Simulateur Amortissement'!B7*12,"",'Simulateur Amortissement'!B13) | F53: =IF(B53="","",B53+E53) | G53: =G52-D53
A54: 51 | B54: =IF(A54>'Simulateur Amortissement'!B7*12,"",'Simulateur Amortissement'!B12) | C54: =G53*'Simulateur Amortissement'!B6/12 | D54: =IF(B54="","",B54-C54) | E54: =IF(A54>'Simulateur Amortissement'!B7*12,"",'Simulateur Amortissement'!B13) | F54: =IF(B54="","",B54+E54) | G54: =G53-D54
A55: 52 | B55: =IF(A55>'Simulateur Amortissement'!B7*12,"",'Simulateur Amortissement'!B12) | C55: =G54*'Simulateur Amortissement'!B6/12 | D55: =IF(B55="","",B55-C55) | E55: =IF(A55>'Simulateur Amortissement'!B7*12,"",'Simulateur Amortissement'!B13) | F55: =IF(B55="","",B55+E55) | G55: =G54-D55
A56: 53 | B56: =IF(A56>'Simulateur Amortissement'!B7*12,"",'Simulateur Amortissement'!B12) | C56: =G55*'Simulateur Amortissement'!B6/12 | D56: =IF(B56="","",B56-C56) | E56: =IF(A56>'Simulateur Amortissement'!B7*12,"",'Simulateur Amortissement'!B13) | F56: =IF(B56="","",B56+E56) | G56: =G55-D56
A57: 54 | B57: =IF(A57>'Simulateur Amortissement'!B7*12,"",'Simulateur Amortissement'!B12) | C57: =G56*'Simulateur Amortissement'!B6/12 | D57: =IF(B57="","",B57-C57) | E57: =IF(A57>'Simulateur Amortissement'!B7*12,"",'Simulateur Amortissement'!B13) | F57: =IF(B57="","",B57+E57) | G57: =G56-D57
A58: 55 | B58: =IF(A58>'Simulateur Amortissement'!B7*12,"",'Simulateur Amortissement'!B12) | C58: =G57*'Simulateur Amortissement'!B6/12 | D58: =IF(B58="","",B58-C58) | E58: =IF(A58>'Simulateur Amortissement'!B7*12,"",'Simulateur Amortissement'!B13) | F58: =IF(B58="","",B58+E58) | G58: =G57-D58
A59: 56 | B59: =IF(A59>'Simulateur Amortissement'!B7*12,"",'Simulateur Amortissement'!B12) | C59: =G58*'Simulateur Amortissement'!B6/12 | D59: =IF(B59="","",B59-C59) | E59: =IF(A59>'Simulateur Amortissement'!B7*12,"",'Simulateur Amortissement'!B13) | F59: =IF(B59="","",B59+E59) | G59: =G58-D59
A60: 57 | B60: =IF(A60>'Simulateur Amortissement'!B7*12,"",'Simulateur Amortissement'!B12) | C60: =G59*'Simulateur Amortissement'!B6/12 | D60: =IF(B60="","",B60-C60) | E60: =IF(A60>'Simulateur Amortissement'!B7*12,"",'Simulateur Amortissement'!B13) | F60: =IF(B60="","",B60+E60) | G60: =G59-D60
A61: 58 | B61: =IF(A61>'Simulateur Amortissement'!B7*12,"",'Simulateur Amortissement'!B12) | C61: =G60*'Simulateur Amortissement'!B6/12 | D61: =IF(B61="","",B61-C61) | E61: =IF(A61>'Simulateur Amortissement'!B7*12,"",'Simulateur Amortissement'!B13) | F61: =IF(B61="","",B61+E61) | G61: =G60-D61
A62: 59 | B62: =IF(A62>'Simulateur Amortissement'!B7*12,"",'Simulateur Amortissement'!B12) | C62: =G61*'Simulateur Amortissement'!B6/12 | D62: =IF(B62="","",B62-C62) | E62: =IF(A62>'Simulateur Amortissement'!B7*12,"",'Simulateur Amortissement'!B13) | F62: =IF(B62="","",B62+E62) | G62: =G61-D62
A63: 60 | B63: =IF(A63>'Simulateur Amortissement'!B7*12,"",'Simulateur Amortissement'!B12) | C63: =G62*'Simulateur Amortissement'!B6/12 | D63: =IF(B63="","",B63-C63) | E63: =IF(A63>'Simulateur Amortissement'!B7*12,"",'Simulateur Amortissement'!B13) | F63: =IF(B63="","",B63+E63) | G63: =G62-D63
A64: 61 | B64: =IF(A64>'Simulateur Amortissement'!B7*12,"",'Simulateur Amortissement'!B12) | C64: =G63*'Simulateur Amortissement'!B6/12 | D64: =IF(B64="","",B64-C64) | E64: =IF(A64>'Simulateur Amortissement'!B7*12,"",'Simulateur Amortissement'!B13) | F64: =IF(B64="","",B64+E64) | G64: =G63-D64
A65: 62 | B65: =IF(A65>'Simulateur Amortissement'!B7*12,"",'Simulateur Amortissement'!B12) | C65: =G64*'Simulateur Amortissement'!B6/12 | D65: =IF(B65="","",B65-C65) | E65: =IF(A65>'Simulateur Amortissement'!B7*12,"",'Simulateur Amortissement'!B13) | F65: =IF(B65="","",B65+E65) | G65: =G64-D65
A66: 63 | B66: =IF(A66>'Simulateur Amortissement'!B7*12,"",'Simulateur Amortissement'!B12) | C66: =G65*'Simulateur Amortissement'!B6/12 | D66: =IF(B66="","",B66-C66) | E66: =IF(A66>'Simulateur Amortissement'!B7*12,"",'Simulateur Amortissement'!B13) | F66: =IF(B66="","",B66+E66) | G66: =G65-D66
A67: 64 | B67: =IF(A67>'Simulateur Amortissement'!B7*12,"",'Simulateur Amortissement'!B12) | C67: =G66*'Simulateur Amortissement'!B6/12 | D67: =IF(B67="","",B67-C67) | E67: =IF(A67>'Simulateur Amortissement'!B7*12,"",'Simulateur Amortissement'!B13) | F67: =IF(B67="","",B67+E67) | G67: =G66-D67
A68: 65 | B68: =IF(A68>'Simulateur Amortissement'!B7*12,"",'Simulateur Amortissement'!B12) | C68: =G67*'Simulateur Amortissement'!B6/12 | D68: =IF(B68="","",B68-C68) | E68: =IF(A68>'Simulateur Amortissement'!B7*12,"",'Simulateur Amortissement'!B13) | F68: =IF(B68="","",B68+E68) | G68: =G67-D68
A69: 66 | B69: =IF(A69>'Simulateur Amortissement'!B7*12,"",'Simulateur Amortissement'!B12) | C69: =G68*'Simulateur Amortissement'!B6/12 | D69: =IF(B69="","",B69-C69) | E69: =IF(A69>'Simulateur Amortissement'!B7*12,"",'Simulateur Amortissement'!B13) | F69: =IF(B69="","",B69+E69) | G69: =G68-D69
A70: 67 | B70: =IF(A70>'Simulateur Amortissement'!B7*12,"",'Simulateur Amortissement'!B12) | C70: =G69*'Simulateur Amortissement'!B6/12 | D70: =IF(B70="","",B70-C70) | E70: =IF(A70>'Simulateur Amortissement'!B7*12,"",'Simulateur Amortissement'!B13) | F70: =IF(B70="","",B70+E70) | G70: =G69-D70
A71: 68 | B71: =IF(A71>'Simulateur Amortissement'!B7*12,"",'Simulateur Amortissement'!B12) | C71: =G70*'Simulateur Amortissement'!B6/12 | D71: =IF(B71="","",B71-C71) | E71: =IF(A71>'Simulateur Amortissement'!B7*12,"",'Simulateur Amortissement'!B13) | F71: =IF(B71="","",B71+E71) | G71: =G70-D71
A72: 69 | B72: =IF(A72>'Simulateur Amortissement'!B7*12,"",'Simulateur Amortissement'!B12) | C72: =G71*'Simulateur Amortissement'!B6/12 | D72: =IF(B72="","",B72-C72) | E72: =IF(A72>'Simulateur Amortissement'!B7*12,"",'Simulateur Amortissement'!B13) | F72: =IF(B72="","",B72+E72) | G72: =G71-D72
A73: 70 | B73: =IF(A73>'Simulateur Amortissement'!B7*12,"",'Simulateur Amortissement'!B12) | C73: =G72*'Simulateur Amortissement'!B6/12 | D73: =IF(B73="","",B73-C73) | E73: =IF(A73>'Simulateur Amortissement'!B7*12,"",'Simulateur Amortissement'!B13) | F73: =IF(B73="","",B73+E73) | G73: =G72-D73
A74: 71 | B74: =IF(A74>'Simulateur Amortissement'!B7*12,"",'Simulateur Amortissement'!B12) | C74: =G73*'Simulateur Amortissement'!B6/12 | D74: =IF(B74="","",B74-C74) | E74: =IF(A74>'Simulateur Amortissement'!B7*12,"",'Simulateur Amortissement'!B13) | F74: =IF(B74="","",B74+E74) | G74: =G73-D74
A75: 72 | B75: =IF(A75>'Simulateur Amortissement'!B7*12,"",'Simulateur Amortissement'!B12) | C75: =G74*'Simulateur Amortissement'!B6/12 | D75: =IF(B75="","",B75-C75) | E75: =IF(A75>'Simulateur Amortissement'!B7*12,"",'Simulateur Amortissement'!B13) | F75: =IF(B75="","",B75+E75) | G75: =G74-D75
A76: 73 | B76: =IF(A76>'Simulateur Amortissement'!B7*12,"",'Simulateur Amortissement'!B12) | C76: =G75*'Simulateur Amortissement'!B6/12 | D76: =IF(B76="","",B76-C76) | E76: =IF(A76>'Simulateur Amortissement'!B7*12,"",'Simulateur Amortissement'!B13) | F76: =IF(B76="","",B76+E76) | G76: =G75-D76
A77: 74 | B77: =IF(A77>'Simulateur Amortissement'!B7*12,"",'Simulateur Amortissement'!B12) | C77: =G76*'Simulateur Amortissement'!B6/12 | D77: =IF(B77="","",B77-C77) | E77: =IF(A77>'Simulateur Amortissement'!B7*12,"",'Simulateur Amortissement'!B13) | F77: =IF(B77="","",B77+E77) | G77: =G76-D77
A78: 75 | B78: =IF(A78>'Simulateur Amortissement'!B7*12,"",'Simulateur Amortissement'!B12) | C78: =G77*'Simulateur Amortissement'!B6/12 | D78: =IF(B78="","",B78-C78) | E78: =IF(A78>'Simulateur Amortissement'!B7*12,"",'Simulateur Amortissement'!B13) | F78: =IF(B78="","",B78+E78) | G78: =G77-D78
A79: 76 | B79: =IF(A79>'Simulateur Amortissement'!B7*12,"",'Simulateur Amortissement'!B12) | C79: =G78*'Simulateur Amortissement'!B6/12 | D79: =IF(B79="","",B79-C79) | E79: =IF(A79>'Simulateur Amortissement'!B7*12,"",'Simulateur Amortissement'!B13) | F79: =IF(B79="","",B79+E79) | G79: =G78-D79
A80: 77 | B80: =IF(A80>'Simulateur Amortissement'!B7*12,"",'Simulateur Amortissement'!B12) | C80: =G79*'Simulateur Amortissement'!B6/12 | D80: =IF(B80="","",B80-C80) | E80: =IF(A80>'Simulateur Amortissement'!B7*12,"",'Simulateur Amortissement'!B13) | F80: =IF(B80="","",B80+E80) | G80: =G79-D80
A81: 78 | B81: =IF(A81>'Simulateur Amortissement'!B7*12,"",'Simulateur Amortissement'!B12) | C81: =G80*'Simulateur Amortissement'!B6/12 | D81: =IF(B81="","",B81-C81) | E81: =IF(A81>'Simulateur Amortissement'!B7*12,"",'Simulateur Amortissement'!B13) | F81: =IF(B81="","",B81+E81) | G81: =G80-D81
A82: 79 | B82: =IF(A82>'Simulateur Amortissement'!B7*12,"",'Simulateur Amortissement'!B12) | C82: =G81*'Simulateur Amortissement'!B6/12 | D82: =IF(B82="","",B82-C82) | E82: =IF(A82>'Simulateur Amortissement'!B7*12,"",'Simulateur Amortissement'!B13) | F82: =IF(B82="","",B82+E82) | G82: =G81-D82
A83: 80 | B83: =IF(A83>'Simulateur Amortissement'!B7*12,"",'Simulateur Amortissement'!B12) | C83: =G82*'Simulateur Amortissement'!B6/12 | D83: =IF(B83="","",B83-C83) | E83: =IF(A83>'Simulateur Amortissement'!B7*12,"",'Simulateur Amortissement'!B13) | F83: =IF(B83="","",B83+E83) | G83: =G82-D83
A84: 81 | B84: =IF(A84>'Simulateur Amortissement'!B7*12,"",'Simulateur Amortissement'!B12) | C84: =G83*'Simulateur Amortissement'!B6/12 | D84: =IF(B84="","",B84-C84) | E84: =IF(A84>'Simulateur Amortissement'!B7*12,"",'Simulateur Amortissement'!B13) | F84: =IF(B84="","",B84+E84) | G84: =G83-D84
A85: 82 | B85: =IF(A85>'Simulateur Amortissement'!B7*12,"",'Simulateur Amortissement'!B12) | C85: =G84*'Simulateur Amortissement'!B6/12 | D85: =IF(B85="","",B85-C85) | E85: =IF(A85>'Simulateur Amortissement'!B7*12,"",'Simulateur Amortissement'!B13) | F85: =IF(B85="","",B85+E85) | G85: =G84-D85
A86: 83 | B86: =IF(A86>'Simulateur Amortissement'!B7*12,"",'Simulateur Amortissement'!B12) | C86: =G85*'Simulateur Amortissement'!B6/12 | D86: =IF(B86="","",B86-C86) | E86: =IF(A86>'Simulateur Amortissement'!B7*12,"",'Simulateur Amortissement'!B13) | F86: =IF(B86="","",B86+E86) | G86: =G85-D86
A87: 84 | B87: =IF(A87>'Simulateur Amortissement'!B7*12,"",'Simulateur Amortissement'!B12) | C87: =G86*'Simulateur Amortissement'!B6/12 | D87: =IF(B87="","",B87-C87) | E87: =IF(A87>'Simulateur Amortissement'!B7*12,"",'Simulateur Amortissement'!B13) | F87: =IF(B87="","",B87+E87) | G87: =G86-D87
A88: 85 | B88: =IF(A88>'Simulateur Amortissement'!B7*12,"",'Simulateur Amortissement'!B12) | C88: =G87*'Simulateur Amortissement'!B6/12 | D88: =IF(B88="","",B88-C88) | E88: =IF(A88>'Simulateur Amortissement'!B7*12,"",'Simulateur Amortissement'!B13) | F88: =IF(B88="","",B88+E88) | G88: =G87-D88
A89: 86 | B89: =IF(A89>'Simulateur Amortissement'!B7*12,"",'Simulateur Amortissement'!B12) | C89: =G88*'Simulateur Amortissement'!B6/12 | D89: =IF(B89="","",B89-C89) | E89: =IF(A89>'Simulateur Amortissement'!B7*12,"",'Simulateur Amortissement'!B13) | F89: =IF(B89="","",B89+E89) | G89: =G88-D89
A90: 87 | B90: =IF(A90>'Simulateur Amortissement'!B7*12,"",'Simulateur Amortissement'!B12) | C90: =G89*'Simulateur Amortissement'!B6/12 | D90: =IF(B90="","",B90-C90) | E90: =IF(A90>'Simulateur Amortissement'!B7*12,"",'Simulateur Amortissement'!B13) | F90: =IF(B90="","",B90+E90) | G90: =G89-D90
A91: 88 | B91: =IF(A91>'Simulateur Amortissement'!B7*12,"",'Simulateur Amortissement'!B12) | C91: =G90*'Simulateur Amortissement'!B6/12 | D91: =IF(B91="","",B91-C91) | E91: =IF(A91>'Simulateur Amortissement'!B7*12,"",'Simulateur Amortissement'!B13) | F91: =IF(B91="","",B91+E91) | G91: =G90-D91
A92: 89 | B92: =IF(A92>'Simulateur Amortissement'!B7*12,"",'Simulateur Amortissement'!B12) | C92: =G91*'Simulateur Amortissement'!B6/12 | D92: =IF(B92="","",B92-C92) | E92: =IF(A92>'Simulateur Amortissement'!B7*12,"",'Simulateur Amortissement'!B13) | F92: =IF(B92="","",B92+E92) | G92: =G91-D92
A93: 90 | B93: =IF(A93>'Simulateur Amortissement'!B7*12,"",'Simulateur Amortissement'!B12) | C93: =G92*'Simulateur Amortissement'!B6/12 | D93: =IF(B93="","",B93-C93) | E93: =IF(A93>'Simulateur Amortissement'!B7*12,"",'Simulateur Amortissement'!B13) | F93: =IF(B93="","",B93+E93) | G93: =G92-D93
A94: 91 | B94: =IF(A94>'Simulateur Amortissement'!B7*12,"",'Simulateur Amortissement'!B12) | C94: =G93*'Simulateur Amortissement'!B6/12 | D94: =IF(B94="","",B94-C94) | E94: =IF(A94>'Simulateur Amortissement'!B7*12,"",'Simulateur Amortissement'!B13) | F94: =IF(B94="","",B94+E94) | G94: =G93-D94
A95: 92 | B95: =IF(A95>'Simulateur Amortissement'!B7*12,"",'Simulateur Amortissement'!B12) | C95: =G94*'Simulateur Amortissement'!B6/12 | D95: =IF(B95="","",B95-C95) | E95: =IF(A95>'Simulateur Amortissement'!B7*12,"",'Simulateur Amortissement'!B13) | F95: =IF(B95="","",B95+E95) | G95: =G94-D95
A96: 93 | B96: =IF(A96>'Simulateur Amortissement'!B7*12,"",'Simulateur Amortissement'!B12) | C96: =G95*'Simulateur Amortissement'!B6/12 | D96: =IF(B96="","",B96-C96) | E96: =IF(A96>'Simulateur Amortissement'!B7*12,"",'Simulateur Amortissement'!B13) | F96: =IF(B96="","",B96+E96) | G96: =G95-D96
A97: 94 | B97: =IF(A97>'Simulateur Amortissement'!B7*12,"",'Simulateur Amortissement'!B12) | C97: =G96*'Simulateur Amortissement'!B6/12 | D97: =IF(B97="","",B97-C97) | E97: =IF(A97>'Simulateur Amortissement'!B7*12,"",'Simulateur Amortissement'!B13) | F97: =IF(B97="","",B97+E97) | G97: =G96-D97
A98: 95 | B98: =IF(A98>'Simulateur Amortissement'!B7*12,"",'Simulateur Amortissement'!B12) | C98: =G97*'Simulateur Amortissement'!B6/12 | D98: =IF(B98="","",B98-C98) | E98: =IF(A98>'Simulateur Amortissement'!B7*12,"",'Simulateur Amortissement'!B13) | F98: =IF(B98="","",B98+E98) | G98: =G97-D98
A99: 96 | B99: =IF(A99>'Simulateur Amortissement'!B7*12,"",'Simulateur Amortissement'!B12) | C99: =G98*'Simulateur Amortissement'!B6/12 | D99: =IF(B99="","",B99-C99) | E99: =IF(A99>'Simulateur Amortissement'!B7*12,"",'Simulateur Amortissement'!B13) | F99: =IF(B99="","",B99+E99) | G99: =G98-D99
A100: 97 | B100: =IF(A100>'Simulateur Amortissement'!B7*12,"",'Simulateur Amortissement'!B12) | C100: =G99*'Simulateur Amortissement'!B6/12 | D100: =IF(B100="","",B100-C100) | E100: =IF(A100>'Simulateur Amortissement'!B7*12,"",'Simulateur Amortissement'!B13) | F100: =IF(B100="","",B100+E100) | G100: =G99-D100
A101: 98 | B101: =IF(A101>'Simulateur Amortissement'!B7*12,"",'Simulateur Amortissement'!B12) | C101: =G100*'Simulateur Amortissement'!B6/12 | D101: =IF(B101="","",B101-C101) | E101: =IF(A101>'Simulateur Amortissement'!B7*12,"",'Simulateur Amortissement'!B13) | F101: =IF(B101="","",B101+E101) | G101: =G100-D101
...

Sheet Comparateur Durées
A1: COMPARATEUR DE DURÉES DE CRÉDIT
B3: 10 ans | C3: 15 ans | D3: 20 ans | E3: 25 ans
A4: Nombre de mensualités | B4: =10*12 | C4: =15*12 | D4: =20*12 | E4: =25*12
A5: Mensualité (hors assurance) | B5: =-PMT('Simulateur Amortissement'!B6/12,10*12,'Simulateur Amortissement'!B5) | C5: =-PMT('Simulateur Amortissement'!B6/12,15*12,'Simulateur Amortissement'!B5) | D5: =-PMT('Simulateur Amortissement'!B6/12,20*12,'Simulateur Amortissement'!B5) | E5: =-PMT('Simulateur Amortissement'!B6/12,25*12,'Simulateur Amortissement'!B5)
A6: Mensualité assurance | B6: ='Simulateur Amortissement'!B13 | C6: ='Simulateur Amortissement'!B13 | D6: ='Simulateur Amortissement'!B13 | E6: ='Simulateur Amortissement'!B13
A7: Mensualité totale | B7: =B5+B6 | C7: =C5+C6 | D7: =D5+D6 | E7: =E5+E6
A8: Total intérêts | B8: =-PMT('Simulateur Amortissement'!B6/12,10*12,'Simulateur Amortissement'!B5)*10*12-'Simulateur Amortissement'!B5 | C8: =-PMT('Simulateur Amortissement'!B6/12,15*12,'Simulateur Amortissement'!B5)*15*12-'Simulateur Amortissement'!B5 | D8: =-PMT('Simulateur Amortissement'!B6/12,20*12,'Simulateur Amortissement'!B5)*20*12-'Simulateur Amortissement'!B5 | E8: =-PMT('Simulateur Amortissement'!B6/12,25*12,'Simulateur Amortissement'!B5)*25*12-'Simulateur Amortissement'!B5
A9: Total assurance | B9: ='Simulateur Amortissement'!B13*10*12 | C9: ='Simulateur Amortissement'!B13*15*12 | D9: ='Simulateur Amortissement'!B13*20*12 | E9: ='Simulateur Amortissement'!B13*25*12
A10: Coût total du crédit | B10: =B8+B9 | C10: =C8+C9 | D10: =D8+D9 | E10: =E8+E9
A12: 💡 ANALYSE :
A13: Plus la durée est longue, plus la mensualité est basse (meilleur cashflow) mais plus le coût total est élevé. L'investisseur immobilier privilégie souvent 20-25 ans pour maximiser le cashflow et utiliser l'effet de levier. L'argent économisé sur les mensualités peut être réinvesti dans un nouveau bien.
